{
  "010-general": {
    "title": "General"
  },
  "020-components": {
    "title": "Components"
  },
  "030-views": {
    "title": "Views"
  },
  "110-seed-builder": {
    "title": "Seed Builder"
  },
  "210-deployment": {
    "title": "Deployment",
    "children": {
      "220-ubuntu": {
        "title": "Ubuntu 18.04"
      },
       "230-eb-single-instance": {
        "title": "AWS EB single instance"
      },
      "240-eb-load-balanced": {
        "title": "AWS EB load balanced"
      }
    }
  }
}